funcnodes_worker/__init__.py
funcnodes_worker/_opts.py
funcnodes_worker/external_worker.py
funcnodes_worker/loop.py
funcnodes_worker/message_queue_worker.py
funcnodes_worker/remote_worker.py
funcnodes_worker/socket.py
funcnodes_worker/websocket.py
funcnodes_worker/worker.py
funcnodes_worker/utils/__init__.py
funcnodes_worker/utils/messages.py
funcnodes_worker/utils/modules.py
funcnodes_worker-1.5.1.dist-info/METADATA
funcnodes_worker-1.5.1.dist-info/WHEEL
funcnodes_worker-1.5.1.dist-info/licenses/LICENSE
funcnodes_worker-1.5.1.dist-info/RECORD
