Metadata-Version: 2.4
Name: funcnodes-worker
Version: 1.5.1
Summary: Worker package for FuncNodes
Project-URL: homepage, https://github.com/Linkdlab/funcnodes_worker
Project-URL: source, https://github.com/Linkdlab/funcnodes_worker
Project-URL: tracker, https://github.com/Linkdlab/funcnodes_worker/issues
Project-URL: download, https://pypi.org/project/funcnodes_worker/#files
Author-email: Julian Kimmig <julian.kimmig@linkdlab.de>
License: AGPL-3.0
License-File: LICENSE
Requires-Python: >=3.11
Requires-Dist: asynctoolkit>=0.1.1
Requires-Dist: funcnodes-core>=2.2.0
Requires-Dist: packaging>=24.2
Requires-Dist: pip>=25.0.1
Requires-Dist: pydantic>=2.0.0
Requires-Dist: python-slugify>=8.0.4
Provides-Extra: all
Requires-Dist: aiohttp; extra == 'all'
Requires-Dist: aiohttp-cors; extra == 'all'
Requires-Dist: requests; extra == 'all'
Requires-Dist: subprocess-monitor>=0.3.0; extra == 'all'
Requires-Dist: venvmngr>=0.1.15; extra == 'all'
Provides-Extra: http
Requires-Dist: aiohttp; extra == 'http'
Requires-Dist: aiohttp-cors; extra == 'http'
Requires-Dist: requests; extra == 'http'
Provides-Extra: subprocess-monitor
Requires-Dist: subprocess-monitor>=0.3.0; extra == 'subprocess-monitor'
Provides-Extra: venv
Requires-Dist: venvmngr>=0.1.15; extra == 'venv'
